delta_sync/__init__.py
delta_sync/sync.py
delta_sync-0.0.1.dist-info/WHEEL
delta_sync-0.0.1.dist-info/METADATA
delta_sync-0.0.1.dist-info/RECORD
