Metadata-Version: 2.1
Name: delta-sync
Version: 0.0.1
Summary: Syncing delta tables
Home-page: https://github.com/ffinfo/delta-sync
License: MIT
Keywords: pydantic,spark
Author: Peter van 't Hof'
Author-email: pjrvanthof@gmail.com
Requires-Python: >=3.8.1,<4.0
Classifier: License :: OSI Approved :: MIT License
Classifier: Programming Language :: Python :: 3
Classifier: Programming Language :: Python :: 3.9
Classifier: Programming Language :: Python :: 3.10
Classifier: Programming Language :: Python :: 3.11
Provides-Extra: spark
Requires-Dist: delta-spark (>=2.4.0,<3.0.0)
Requires-Dist: pyspark (>=3.4.0,<3.5.0); extra == "spark"
Project-URL: Repository, https://github.com/ffinfo/delta-sync
